deploy_to_kubernetes/__init__.py
deploy_to_kubernetes/scripts/__init__.py
deploy_to_kubernetes-1.0.8.dist-info/LICENSE
deploy_to_kubernetes-1.0.8.dist-info/METADATA
deploy_to_kubernetes-1.0.8.dist-info/WHEEL
deploy_to_kubernetes-1.0.8.dist-info/top_level.txt
deploy_to_kubernetes-1.0.8.dist-info/RECORD
