Metadata-Version: 2.1
Name: deploy-to-kubernetes
Version: 1.0.8
Summary: Deployment tooling for managing a distributed AI stack on Kubernetes. Projects using this tool: AntiNex (https://antinex.readthedocs.io/en/latest/) and the Stock Analysis Engine (https://stock-analysis-engine.readthedocs.io/en/latest/) and works on Kubernetes 1.13.3
Home-page: https://github.com/jay-johnson/deploy-to-kubernetes
Author: Jay Johnson
Author-email: jay.p.h.johnson@gmail.com
License: UNKNOWN
Platform: UNKNOWN
Classifier: Development Status :: 5 - Production/Stable
Classifier: Intended Audience :: Developers
Classifier: License :: OSI Approved :: Apache Software License
Classifier: Operating System :: OS Independent
Classifier: Programming Language :: Python :: 3.6
Classifier: Programming Language :: Python :: Implementation :: PyPy
Classifier: Topic :: Software Development :: Libraries :: Python Modules
Requires-Dist: ansible
Requires-Dist: colorlog
Requires-Dist: coverage
Requires-Dist: flake8 (<=3.4.1)
Requires-Dist: pep8 (>=1.7.1)
Requires-Dist: pipenv
Requires-Dist: pycodestyle (<=2.3.1)
Requires-Dist: pylint
Requires-Dist: recommonmark
Requires-Dist: sphinx
Requires-Dist: sphinx-autobuild
Requires-Dist: sphinx-rtd-theme
Requires-Dist: spylunking
Requires-Dist: unittest2
Requires-Dist: mock
